brackette/__init__.py
brackette/memento.py
brackette/time.py
brackette-0.2.1.dist-info/LICENSE
brackette-0.2.1.dist-info/METADATA
brackette-0.2.1.dist-info/WHEEL
brackette-0.2.1.dist-info/top_level.txt
brackette-0.2.1.dist-info/RECORD
