Metadata-Version: 2.1
Name: brackette
Version: 0.2.1
Summary: Package that manages a state using memento design pattern
Home-page: https://github.com/marekyggdrasil/brackette
Author: Marek Narozniak
Author-email: marek.yggdrasil@gmail.com
License: MIT
Platform: UNKNOWN
Classifier: Programming Language :: Python :: 3
Classifier: Programming Language :: Python :: 2
Classifier: License :: OSI Approved :: MIT License
Classifier: Operating System :: OS Independent
License-File: LICENSE
Requires-Dist: diff-match-patch
